kgx/__init__.py
kgx/client.py
kgx/common.py
kgx/exceptions.py
kgx/requests.py
kgx/responses.py
kgx/ecommerce/__init__.py
kgx/ecommerce/oscar/__init__.py
kgx/ecommerce/oscar/methods.py
kgx/ecommerce/oscar/repository.py
kgx_client-0.1.0.dist-info/METADATA
kgx_client-0.1.0.dist-info/WHEEL
kgx_client-0.1.0.dist-info/top_level.txt
kgx_client-0.1.0.dist-info/RECORD
